metasub_utils.data_packet-0.3.0-py3.6-nspkg.pth
metasub_utils/data_packet/__init__.py
metasub_utils/data_packet/clean_metadata.py
metasub_utils/data_packet/cli.py
metasub_utils/data_packet/filter_data_packet.py
metasub_utils.data_packet-0.3.0.dist-info/METADATA
metasub_utils.data_packet-0.3.0.dist-info/RECORD
metasub_utils.data_packet-0.3.0.dist-info/WHEEL
metasub_utils.data_packet-0.3.0.dist-info/entry_points.txt
metasub_utils.data_packet-0.3.0.dist-info/namespace_packages.txt
metasub_utils.data_packet-0.3.0.dist-info/top_level.txt
